README.md
setup.py
caller/__init__.py
caller/base_types.py
caller/helpers.py
caller.egg-info/PKG-INFO
caller.egg-info/SOURCES.txt
caller.egg-info/dependency_links.txt
caller.egg-info/requires.txt
caller.egg-info/top_level.txt