Metadata-Version: 2.1
Name: caller
Version: 0.0.2
Summary: Set a Python property using a function call
Home-page: https://github.com/vtitor/caller
Author: Victor Titor
Author-email: vtitor.edumix@gmail.com
License: UNKNOWN
Platform: UNKNOWN
Classifier: Programming Language :: Python
Classifier: Programming Language :: Python :: 2.7
Classifier: Programming Language :: Python :: 3.6
Provides-Extra: dev
